django_hexdi-0.2.1.dist-info/DESCRIPTION.rst
django_hexdi-0.2.1.dist-info/METADATA
django_hexdi-0.2.1.dist-info/RECORD
django_hexdi-0.2.1.dist-info/WHEEL
django_hexdi-0.2.1.dist-info/metadata.json
django_hexdi-0.2.1.dist-info/top_level.txt
djhexdi/__init__.py
djhexdi/admin.py
djhexdi/apps.py
djhexdi/models.py
djhexdi/settings.py
djhexdi/strategy.py
djhexdi/tests.py
djhexdi/views.py
djhexdi/management/__init__.py
djhexdi/management/commands/__init__.py
djhexdi/management/commands/di_find.py
