Metadata-Version: 2.0
Name: django-hexdi
Version: 0.2.1
Summary: Highly extensible Dependency injection framework for humans. Django integration
Home-page: https://github.com/zibertscrem/django-hexdi
Author: Dmitriy Selischev
Author-email: zibertscrem@gmail.com
License: MIT
Platform: UNKNOWN
Classifier: Development Status :: 5 - Production/Stable
Classifier: Intended Audience :: Developers
Classifier: Topic :: Software Development :: Libraries :: Application Frameworks
Classifier: License :: OSI Approved :: MIT License
Classifier: Programming Language :: Python :: 3.5
Classifier: Programming Language :: Python :: 3.6
Requires-Python: >=3.5,<4
Requires-Dist: typing
Requires-Dist: hexdi (==0.2.1)
